{
  "user": {
    "userId": "synth_27",
    "age": null,
    "gender": null,
    "location": {
      "city": "Singapore",
      "country": "SG"
    },
    "device": {
      "platform": null,
      "appVersion": null
    }
  },
  "interaction": {
    "views": [
      {
        "timestamp": "2012-07-03T00:26:06+00:00",
        "poiId": "4cfdbb9834c1a093c1fe510e",
        "poiCategories": [
          "Factory"
        ],
        "poiSubcategories": [],
        "duration": null,
        "referrer": null,
        "userLocation": {
          "latitude": 1.313943,
          "longitude": 103.753268
        }
      },
      {
        "timestamp": "2012-07-04T00:44:05+00:00",
        "poiId": "4cfdbb9834c1a093c1fe510e",
        "poiCategories": [
          "Factory"
        ],
        "poiSubcategories": [],
        "duration": null,
        "referrer": null,
        "userLocation": {
          "latitude": 1.313943,
          "longitude": 103.753268
        }
      },
      {
        "timestamp": "2012-07-05T01:55:08+00:00",
        "poiId": "4cfdbb9834c1a093c1fe510e",
        "poiCategories": [
          "Factory"
        ],
        "poiSubcategories": [],
        "duration": null,
        "referrer": null,
        "userLocation": {
          "latitude": 1.313943,
          "longitude": 103.753268
        }
      },
      {
        "timestamp": "2012-07-05T04:23:23+00:00",
        "poiId": "4c5ff63d13791b8d8e5f4eaf",
        "poiCategories": [
          "Food Court"
        ],
        "poiSubcategories": [],
        "duration": null,
        "referrer": null,
        "userLocation": {
          "latitude": 1.311866,
          "longitude": 103.759748
        }
      },
      {
        "timestamp": "2012-07-06T00:44:49+00:00",
        "poiId": "4cfdbb9834c1a093c1fe510e",
        "poiCategories": [
          "Factory"
        ],
        "poiSubcategories": [],
        "duration": null,
        "referrer": null,
        "userLocation": {
          "latitude": 1.313943,
          "longitude": 103.753268
        }
      },
      {
        "timestamp": "2012-07-07T08:55:40+00:00",
        "poiId": "4c384f3e93db0f474f592192",
        "poiCategories": [
          "Flea Market"
        ],
        "poiSubcategories": [],
        "duration": null,
        "referrer": null,
        "userLocation": {
          "latitude": 1.300524,
          "longitude": 103.854967
        }
      },
      {
        "timestamp": "2012-07-07T10:46:46+00:00",
        "poiId": "4bb9c1a6935e9521d3512790",
        "poiCategories": [
          "Mall"
        ],
        "poiSubcategories": [],
        "duration": null,
        "referrer": null,
        "userLocation": {
          "latitude": 1.299129,
          "longitude": 103.855391
        }
      },
      {
        "timestamp": "2012-07-09T00:39:04+00:00",
        "poiId": "4cfdbb9834c1a093c1fe510e",
        "poiCategories": [
          "Factory"
        ],
        "poiSubcategories": [],
        "duration": null,
        "referrer": null,
        "userLocation": {
          "latitude": 1.313943,
          "longitude": 103.753268
        }
      },
      {
        "timestamp": "2012-07-12T00:10:38+00:00",
        "poiId": "4cfdbb9834c1a093c1fe510e",
        "poiCategories": [
          "Factory"
        ],
        "poiSubcategories": [],
        "duration": null,
        "referrer": null,
        "userLocation": {
          "latitude": 1.313943,
          "longitude": 103.753268
        }
      },
      {
        "timestamp": "2012-07-13T00:25:49+00:00",
        "poiId": "4cfdbb9834c1a093c1fe510e",
        "poiCategories": [
          "Factory"
        ],
        "poiSubcategories": [],
        "duration": null,
        "referrer": null,
        "userLocation": {
          "latitude": 1.313943,
          "longitude": 103.753268
        }
      },
      {
        "timestamp": "2012-08-10T11:19:11+00:00",
        "poiId": "4b645cdbf964a5205dad2ae3",
        "poiCategories": [
          "Farm"
        ],
        "poiSubcategories": [],
        "duration": null,
        "referrer": null,
        "userLocation": {
          "latitude": 1.320581,
          "longitude": 103.708727
        }
      },
      {
        "timestamp": "2012-08-12T10:04:30+00:00",
        "poiId": "4da84e4793a021ab13c61abf",
        "poiCategories": [
          "Pool Hall"
        ],
        "poiSubcategories": [],
        "duration": null,
        "referrer": null,
        "userLocation": {
          "latitude": 1.329802,
          "longitude": 103.681328
        }
      },
      {
        "timestamp": "2012-10-28T09:01:27+00:00",
        "poiId": "4e6ac2fcd164c37bf4bc1538",
        "poiCategories": [
          "Clothing Store"
        ],
        "poiSubcategories": [],
        "duration": null,
        "referrer": null,
        "userLocation": {
          "latitude": 1.302752,
          "longitude": 103.836154
        }
      },
      {
        "timestamp": "2012-11-06T00:43:01+00:00",
        "poiId": "4b1537bbf964a5206ea923e3",
        "poiCategories": [
          "Train Station"
        ],
        "poiSubcategories": [],
        "duration": null,
        "referrer": null,
        "userLocation": {
          "latitude": 1.294471,
          "longitude": 103.805967
        }
      },
      {
        "timestamp": "2012-11-17T11:34:46+00:00",
        "poiId": "4ca945d544a8224bd5462040",
        "poiCategories": [
          "Park"
        ],
        "poiSubcategories": [],
        "duration": null,
        "referrer": null,
        "userLocation": {
          "latitude": 1.292828,
          "longitude": 103.765426
        }
      },
      {
        "timestamp": "2012-12-02T08:41:58+00:00",
        "poiId": "4ec4a1b1e5fa74ea530619fc",
        "poiCategories": [
          "Mall"
        ],
        "poiSubcategories": [],
        "duration": null,
        "referrer": null,
        "userLocation": {
          "latitude": 1.30638,
          "longitude": 103.789322
        }
      },
      {
        "timestamp": "2012-12-02T09:10:44+00:00",
        "poiId": "5034adaae889bef87e8d8536",
        "poiCategories": [
          "Seafood Restaurant"
        ],
        "poiSubcategories": [],
        "duration": null,
        "referrer": null,
        "userLocation": {
          "latitude": 1.306745,
          "longitude": 103.78855
        }
      },
      {
        "timestamp": "2012-12-02T10:38:57+00:00",
        "poiId": "4b4e7e0ff964a520a7ef26e3",
        "poiCategories": [
          "General Entertainment"
        ],
        "poiSubcategories": [],
        "duration": null,
        "referrer": null,
        "userLocation": {
          "latitude": 1.300942,
          "longitude": 103.835886
        }
      },
      {
        "timestamp": "2012-12-04T06:59:55+00:00",
        "poiId": "4b189466f964a52049d423e3",
        "poiCategories": [
          "Mall"
        ],
        "poiSubcategories": [],
        "duration": null,
        "referrer": null,
        "userLocation": {
          "latitude": 1.301339,
          "longitude": 103.8386
        }
      },
      {
        "timestamp": "2012-12-07T03:21:39+00:00",
        "poiId": "4b189466f964a52049d423e3",
        "poiCategories": [
          "Mall"
        ],
        "poiSubcategories": [],
        "duration": null,
        "referrer": null,
        "userLocation": {
          "latitude": 1.301339,
          "longitude": 103.8386
        }
      },
      {
        "timestamp": "2012-12-07T04:39:39+00:00",
        "poiId": "4b4e7e0ff964a520a7ef26e3",
        "poiCategories": [
          "General Entertainment"
        ],
        "poiSubcategories": [],
        "duration": null,
        "referrer": null,
        "userLocation": {
          "latitude": 1.300942,
          "longitude": 103.835886
        }
      },
      {
        "timestamp": "2012-12-13T04:23:06+00:00",
        "poiId": "4b4e7e0ff964a520a7ef26e3",
        "poiCategories": [
          "General Entertainment"
        ],
        "poiSubcategories": [],
        "duration": null,
        "referrer": null,
        "userLocation": {
          "latitude": 1.300942,
          "longitude": 103.835886
        }
      },
      {
        "timestamp": "2012-12-13T13:28:57+00:00",
        "poiId": "4c775cda93faa093a2c5f0fb",
        "poiCategories": [
          "Mall"
        ],
        "poiSubcategories": [],
        "duration": null,
        "referrer": null,
        "userLocation": {
          "latitude": 1.301253,
          "longitude": 103.837023
        }
      },
      {
        "timestamp": "2012-12-15T03:28:58+00:00",
        "poiId": "50697249e4b0cdb23126577a",
        "poiCategories": [
          "Mall"
        ],
        "poiSubcategories": [],
        "duration": null,
        "referrer": null,
        "userLocation": {
          "latitude": 1.301137,
          "longitude": 103.836387
        }
      },
      {
        "timestamp": "2012-12-16T03:05:19+00:00",
        "poiId": "4b0d0c41f964a5206f4323e3",
        "poiCategories": [
          "Subway"
        ],
        "poiSubcategories": [],
        "duration": null,
        "referrer": null,
        "userLocation": {
          "latitude": 1.28452,
          "longitude": 103.851335
        }
      },
      {
        "timestamp": "2012-12-16T03:19:52+00:00",
        "poiId": "50697249e4b0cdb23126577a",
        "poiCategories": [
          "Mall"
        ],
        "poiSubcategories": [],
        "duration": null,
        "referrer": null,
        "userLocation": {
          "latitude": 1.301137,
          "longitude": 103.836387
        }
      },
      {
        "timestamp": "2012-12-16T10:55:40+00:00",
        "poiId": "4b4e7e0ff964a520a7ef26e3",
        "poiCategories": [
          "General Entertainment"
        ],
        "poiSubcategories": [],
        "duration": null,
        "referrer": null,
        "userLocation": {
          "latitude": 1.300942,
          "longitude": 103.835886
        }
      },
      {
        "timestamp": "2012-12-17T03:26:33+00:00",
        "poiId": "4c775cda93faa093a2c5f0fb",
        "poiCategories": [
          "Mall"
        ],
        "poiSubcategories": [],
        "duration": null,
        "referrer": null,
        "userLocation": {
          "latitude": 1.301253,
          "longitude": 103.837023
        }
      },
      {
        "timestamp": "2012-12-17T03:31:38+00:00",
        "poiId": "50697249e4b0cdb23126577a",
        "poiCategories": [
          "Mall"
        ],
        "poiSubcategories": [],
        "duration": null,
        "referrer": null,
        "userLocation": {
          "latitude": 1.301137,
          "longitude": 103.836387
        }
      },
      {
        "timestamp": "2012-12-17T05:03:06+00:00",
        "poiId": "4b4e7e0ff964a520a7ef26e3",
        "poiCategories": [
          "General Entertainment"
        ],
        "poiSubcategories": [],
        "duration": null,
        "referrer": null,
        "userLocation": {
          "latitude": 1.300942,
          "longitude": 103.835886
        }
      },
      {
        "timestamp": "2012-12-18T04:04:34+00:00",
        "poiId": "50697249e4b0cdb23126577a",
        "poiCategories": [
          "Mall"
        ],
        "poiSubcategories": [],
        "duration": null,
        "referrer": null,
        "userLocation": {
          "latitude": 1.301137,
          "longitude": 103.836387
        }
      },
      {
        "timestamp": "2012-12-18T14:02:59+00:00",
        "poiId": "4ea0ec822c5b5cb4f35c7acb",
        "poiCategories": [
          "Ramen /  Noodle House"
        ],
        "poiSubcategories": [],
        "duration": null,
        "referrer": null,
        "userLocation": {
          "latitude": 1.307541,
          "longitude": 103.833216
        }
      },
      {
        "timestamp": "2012-12-20T04:09:00+00:00",
        "poiId": "4b11fc01f964a520d68723e3",
        "poiCategories": [
          "Subway"
        ],
        "poiSubcategories": [],
        "duration": null,
        "referrer": null,
        "userLocation": {
          "latitude": 1.300609,
          "longitude": 103.838568
        }
      },
      {
        "timestamp": "2012-12-20T04:22:31+00:00",
        "poiId": "50697249e4b0cdb23126577a",
        "poiCategories": [
          "Mall"
        ],
        "poiSubcategories": [],
        "duration": null,
        "referrer": null,
        "userLocation": {
          "latitude": 1.301137,
          "longitude": 103.836387
        }
      },
      {
        "timestamp": "2012-12-22T15:11:10+00:00",
        "poiId": "4b4e7e0ff964a520a7ef26e3",
        "poiCategories": [
          "General Entertainment"
        ],
        "poiSubcategories": [],
        "duration": null,
        "referrer": null,
        "userLocation": {
          "latitude": 1.300942,
          "longitude": 103.835886
        }
      },
      {
        "timestamp": "2012-12-22T16:07:54+00:00",
        "poiId": "4bcf09e8ef10952119f98486",
        "poiCategories": [
          "Pool Hall"
        ],
        "poiSubcategories": [],
        "duration": null,
        "referrer": null,
        "userLocation": {
          "latitude": 1.301202,
          "longitude": 103.836856
        }
      },
      {
        "timestamp": "2012-12-23T03:38:04+00:00",
        "poiId": "50697249e4b0cdb23126577a",
        "poiCategories": [
          "Mall"
        ],
        "poiSubcategories": [],
        "duration": null,
        "referrer": null,
        "userLocation": {
          "latitude": 1.301137,
          "longitude": 103.836387
        }
      },
      {
        "timestamp": "2012-12-27T14:34:17+00:00",
        "poiId": "4bcc85e6937ca5932f3aab92",
        "poiCategories": [
          "Food Court"
        ],
        "poiSubcategories": [],
        "duration": null,
        "referrer": null,
        "userLocation": {
          "latitude": 1.314076,
          "longitude": 103.765472
        }
      },
      {
        "timestamp": "2012-12-27T15:45:31+00:00",
        "poiId": "4b0ea1f9f964a520205923e3",
        "poiCategories": [
          "Train Station"
        ],
        "poiSubcategories": [],
        "duration": null,
        "referrer": null,
        "userLocation": {
          "latitude": 1.315291,
          "longitude": 103.765206
        }
      },
      {
        "timestamp": "2012-12-30T03:35:41+00:00",
        "poiId": "50697249e4b0cdb23126577a",
        "poiCategories": [
          "Mall"
        ],
        "poiSubcategories": [],
        "duration": null,
        "referrer": null,
        "userLocation": {
          "latitude": 1.301137,
          "longitude": 103.836387
        }
      },
      {
        "timestamp": "2012-12-31T04:39:31+00:00",
        "poiId": "50697249e4b0cdb23126577a",
        "poiCategories": [
          "Mall"
        ],
        "poiSubcategories": [],
        "duration": null,
        "referrer": null,
        "userLocation": {
          "latitude": 1.301137,
          "longitude": 103.836387
        }
      },
      {
        "timestamp": "2012-12-31T13:27:29+00:00",
        "poiId": "4c775cda93faa093a2c5f0fb",
        "poiCategories": [
          "Mall"
        ],
        "poiSubcategories": [],
        "duration": null,
        "referrer": null,
        "userLocation": {
          "latitude": 1.301253,
          "longitude": 103.837023
        }
      },
      {
        "timestamp": "2012-12-31T21:15:47+00:00",
        "poiId": "4b6e30a8f964a520a1b02ce3",
        "poiCategories": [
          "Fast Food Restaurant"
        ],
        "poiSubcategories": [],
        "duration": null,
        "referrer": null,
        "userLocation": {
          "latitude": 1.306607,
          "longitude": 103.82875
        }
      },
      {
        "timestamp": "2013-01-03T04:37:30+00:00",
        "poiId": "4b11fc01f964a520d68723e3",
        "poiCategories": [
          "Subway"
        ],
        "poiSubcategories": [],
        "duration": null,
        "referrer": null,
        "userLocation": {
          "latitude": 1.300609,
          "longitude": 103.838568
        }
      },
      {
        "timestamp": "2013-01-09T04:35:56+00:00",
        "poiId": "4b11fc01f964a520d68723e3",
        "poiCategories": [
          "Subway"
        ],
        "poiSubcategories": [],
        "duration": null,
        "referrer": null,
        "userLocation": {
          "latitude": 1.300609,
          "longitude": 103.838568
        }
      },
      {
        "timestamp": "2013-01-09T14:48:36+00:00",
        "poiId": "4f5c9b0be4b06784f8a19444",
        "poiCategories": [
          "Arcade"
        ],
        "poiSubcategories": [],
        "duration": null,
        "referrer": null,
        "userLocation": {
          "latitude": 1.301128,
          "longitude": 103.836364
        }
      },
      {
        "timestamp": "2013-01-09T15:21:43+00:00",
        "poiId": "4c02034cf815a593103c0a96",
        "poiCategories": [
          "Fast Food Restaurant"
        ],
        "poiSubcategories": [],
        "duration": null,
        "referrer": null,
        "userLocation": {
          "latitude": 1.300867,
          "longitude": 103.836282
        }
      },
      {
        "timestamp": "2013-01-11T03:55:38+00:00",
        "poiId": "4b11fc01f964a520d68723e3",
        "poiCategories": [
          "Subway"
        ],
        "poiSubcategories": [],
        "duration": null,
        "referrer": null,
        "userLocation": {
          "latitude": 1.300609,
          "longitude": 103.838568
        }
      },
      {
        "timestamp": "2013-01-11T04:04:56+00:00",
        "poiId": "50697249e4b0cdb23126577a",
        "poiCategories": [
          "Mall"
        ],
        "poiSubcategories": [],
        "duration": null,
        "referrer": null,
        "userLocation": {
          "latitude": 1.301137,
          "longitude": 103.836387
        }
      },
      {
        "timestamp": "2013-01-11T09:44:02+00:00",
        "poiId": "4c775cda93faa093a2c5f0fb",
        "poiCategories": [
          "Mall"
        ],
        "poiSubcategories": [],
        "duration": null,
        "referrer": null,
        "userLocation": {
          "latitude": 1.301253,
          "longitude": 103.837023
        }
      },
      {
        "timestamp": "2013-01-11T09:48:21+00:00",
        "poiId": "4b7553ecf964a52088062ee3",
        "poiCategories": [
          "Fried Chicken Joint"
        ],
        "poiSubcategories": [],
        "duration": null,
        "referrer": null,
        "userLocation": {
          "latitude": 1.30107,
          "longitude": 103.83667
        }
      },
      {
        "timestamp": "2013-01-11T10:44:16+00:00",
        "poiId": "4d4d116cf8292d43506969d6",
        "poiCategories": [
          "Tea Room"
        ],
        "poiSubcategories": [],
        "duration": null,
        "referrer": null,
        "userLocation": {
          "latitude": 1.301124,
          "longitude": 103.836164
        }
      },
      {
        "timestamp": "2013-01-12T04:18:20+00:00",
        "poiId": "50697249e4b0cdb23126577a",
        "poiCategories": [
          "Mall"
        ],
        "poiSubcategories": [],
        "duration": null,
        "referrer": null,
        "userLocation": {
          "latitude": 1.301137,
          "longitude": 103.836387
        }
      },
      {
        "timestamp": "2013-01-12T20:58:44+00:00",
        "poiId": "4b8f5fe0f964a520c65233e3",
        "poiCategories": [
          "Food Court"
        ],
        "poiSubcategories": [],
        "duration": null,
        "referrer": null,
        "userLocation": {
          "latitude": 1.264741,
          "longitude": 103.821788
        }
      },
      {
        "timestamp": "2013-01-13T05:22:52+00:00",
        "poiId": "50697249e4b0cdb23126577a",
        "poiCategories": [
          "Mall"
        ],
        "poiSubcategories": [],
        "duration": null,
        "referrer": null,
        "userLocation": {
          "latitude": 1.301137,
          "longitude": 103.836387
        }
      },
      {
        "timestamp": "2013-01-13T14:15:35+00:00",
        "poiId": "4b11fc01f964a520d68723e3",
        "poiCategories": [
          "Subway"
        ],
        "poiSubcategories": [],
        "duration": null,
        "referrer": null,
        "userLocation": {
          "latitude": 1.300609,
          "longitude": 103.838568
        }
      },
      {
        "timestamp": "2013-01-15T04:44:15+00:00",
        "poiId": "4b11fc01f964a520d68723e3",
        "poiCategories": [
          "Subway"
        ],
        "poiSubcategories": [],
        "duration": null,
        "referrer": null,
        "userLocation": {
          "latitude": 1.300609,
          "longitude": 103.838568
        }
      },
      {
        "timestamp": "2013-01-15T09:13:58+00:00",
        "poiId": "4d4d116cf8292d43506969d6",
        "poiCategories": [
          "Tea Room"
        ],
        "poiSubcategories": [],
        "duration": null,
        "referrer": null,
        "userLocation": {
          "latitude": 1.301124,
          "longitude": 103.836164
        }
      },
      {
        "timestamp": "2013-01-15T10:12:05+00:00",
        "poiId": "4c0b19d7340720a1fab68793",
        "poiCategories": [
          "Coffee Shop"
        ],
        "poiSubcategories": [],
        "duration": null,
        "referrer": null,
        "userLocation": {
          "latitude": 1.300953,
          "longitude": 103.836422
        }
      },
      {
        "timestamp": "2013-01-18T08:49:37+00:00",
        "poiId": "4c02034cf815a593103c0a96",
        "poiCategories": [
          "Fast Food Restaurant"
        ],
        "poiSubcategories": [],
        "duration": null,
        "referrer": null,
        "userLocation": {
          "latitude": 1.300867,
          "longitude": 103.836282
        }
      },
      {
        "timestamp": "2013-01-18T11:03:27+00:00",
        "poiId": "4b4e7e0ff964a520a7ef26e3",
        "poiCategories": [
          "General Entertainment"
        ],
        "poiSubcategories": [],
        "duration": null,
        "referrer": null,
        "userLocation": {
          "latitude": 1.300942,
          "longitude": 103.835886
        }
      },
      {
        "timestamp": "2013-01-18T12:40:47+00:00",
        "poiId": "50697249e4b0cdb23126577a",
        "poiCategories": [
          "Mall"
        ],
        "poiSubcategories": [],
        "duration": null,
        "referrer": null,
        "userLocation": {
          "latitude": 1.301137,
          "longitude": 103.836387
        }
      },
      {
        "timestamp": "2013-01-21T08:26:02+00:00",
        "poiId": "4b11fc01f964a520d68723e3",
        "poiCategories": [
          "Subway"
        ],
        "poiSubcategories": [],
        "duration": null,
        "referrer": null,
        "userLocation": {
          "latitude": 1.300609,
          "longitude": 103.838568
        }
      },
      {
        "timestamp": "2013-01-21T08:36:01+00:00",
        "poiId": "4b058815f964a520aeb022e3",
        "poiCategories": [
          "Mall"
        ],
        "poiSubcategories": [],
        "duration": null,
        "referrer": null,
        "userLocation": {
          "latitude": 1.303447,
          "longitude": 103.835668
        }
      },
      {
        "timestamp": "2013-01-21T08:36:34+00:00",
        "poiId": "4b66ca35f964a520f52a2be3",
        "poiCategories": [
          "Boutique"
        ],
        "poiSubcategories": [],
        "duration": null,
        "referrer": null,
        "userLocation": {
          "latitude": 1.303054,
          "longitude": 103.835594
        }
      },
      {
        "timestamp": "2013-01-21T08:48:32+00:00",
        "poiId": "4b4e7e0ff964a520a7ef26e3",
        "poiCategories": [
          "General Entertainment"
        ],
        "poiSubcategories": [],
        "duration": null,
        "referrer": null,
        "userLocation": {
          "latitude": 1.300942,
          "longitude": 103.835886
        }
      },
      {
        "timestamp": "2013-01-26T14:13:42+00:00",
        "poiId": "4dde09c652b155583df8ce22",
        "poiCategories": [
          "Caf\u001a\u001a"
        ],
        "poiSubcategories": [],
        "duration": null,
        "referrer": null,
        "userLocation": {
          "latitude": 1.301232,
          "longitude": 103.836508
        }
      },
      {
        "timestamp": "2013-02-02T15:22:33+00:00",
        "poiId": "4fae21d7e4b0c29a763221a6",
        "poiCategories": [
          "Other Great Outdoors"
        ],
        "poiSubcategories": [],
        "duration": null,
        "referrer": null,
        "userLocation": {
          "latitude": 1.320485,
          "longitude": 103.708734
        }
      },
      {
        "timestamp": "2013-02-03T01:06:41+00:00",
        "poiId": "4fcefbabe4b074e7071afc56",
        "poiCategories": [
          "Church"
        ],
        "poiSubcategories": [],
        "duration": null,
        "referrer": null,
        "userLocation": {
          "latitude": 1.333295,
          "longitude": 103.957293
        }
      },
      {
        "timestamp": "2013-02-03T05:21:37+00:00",
        "poiId": "4c00c741360a9c740808d9a0",
        "poiCategories": [
          "Event Space"
        ],
        "poiSubcategories": [],
        "duration": null,
        "referrer": null,
        "userLocation": {
          "latitude": 1.334993,
          "longitude": 103.959911
        }
      },
      {
        "timestamp": "2013-02-03T06:32:41+00:00",
        "poiId": "4b18e995f964a52079d623e3",
        "poiCategories": [
          "Train Station"
        ],
        "poiSubcategories": [],
        "duration": null,
        "referrer": null,
        "userLocation": {
          "latitude": 1.334504,
          "longitude": 103.961542
        }
      },
      {
        "timestamp": "2013-02-03T07:26:20+00:00",
        "poiId": "4b11fc01f964a520d68723e3",
        "poiCategories": [
          "Subway"
        ],
        "poiSubcategories": [],
        "duration": null,
        "referrer": null,
        "userLocation": {
          "latitude": 1.300609,
          "longitude": 103.838568
        }
      },
      {
        "timestamp": "2013-02-03T07:33:05+00:00",
        "poiId": "50697249e4b0cdb23126577a",
        "poiCategories": [
          "Mall"
        ],
        "poiSubcategories": [],
        "duration": null,
        "referrer": null,
        "userLocation": {
          "latitude": 1.301137,
          "longitude": 103.836387
        }
      },
      {
        "timestamp": "2013-02-03T07:49:33+00:00",
        "poiId": "4dde09c652b155583df8ce22",
        "poiCategories": [
          "Caf\u001a\u001a"
        ],
        "poiSubcategories": [],
        "duration": null,
        "referrer": null,
        "userLocation": {
          "latitude": 1.301232,
          "longitude": 103.836508
        }
      },
      {
        "timestamp": "2013-02-03T08:45:03+00:00",
        "poiId": "4c775cda93faa093a2c5f0fb",
        "poiCategories": [
          "Mall"
        ],
        "poiSubcategories": [],
        "duration": null,
        "referrer": null,
        "userLocation": {
          "latitude": 1.301253,
          "longitude": 103.837023
        }
      },
      {
        "timestamp": "2013-02-03T10:21:55+00:00",
        "poiId": "4bb71a2c941ad13a084a20e3",
        "poiCategories": [
          "Food Court"
        ],
        "poiSubcategories": [],
        "duration": null,
        "referrer": null,
        "userLocation": {
          "latitude": 1.301071,
          "longitude": 103.836905
        }
      },
      {
        "timestamp": "2013-02-03T11:07:35+00:00",
        "poiId": "4b189466f964a52049d423e3",
        "poiCategories": [
          "Mall"
        ],
        "poiSubcategories": [],
        "duration": null,
        "referrer": null,
        "userLocation": {
          "latitude": 1.301339,
          "longitude": 103.8386
        }
      },
      {
        "timestamp": "2013-02-08T11:26:50+00:00",
        "poiId": "4c384f3e93db0f474f592192",
        "poiCategories": [
          "Flea Market"
        ],
        "poiSubcategories": [],
        "duration": null,
        "referrer": null,
        "userLocation": {
          "latitude": 1.300524,
          "longitude": 103.854967
        }
      },
      {
        "timestamp": "2013-02-11T17:33:25+00:00",
        "poiId": "4fae21d7e4b0c29a763221a6",
        "poiCategories": [
          "Other Great Outdoors"
        ],
        "poiSubcategories": [],
        "duration": null,
        "referrer": null,
        "userLocation": {
          "latitude": 1.320485,
          "longitude": 103.708734
        }
      },
      {
        "timestamp": "2013-03-05T16:16:34+00:00",
        "poiId": "4fae21d7e4b0c29a763221a6",
        "poiCategories": [
          "Other Great Outdoors"
        ],
        "poiSubcategories": [],
        "duration": null,
        "referrer": null,
        "userLocation": {
          "latitude": 1.320485,
          "longitude": 103.708734
        }
      },
      {
        "timestamp": "2013-03-06T16:52:19+00:00",
        "poiId": "4b762527f964a520d93f2ee3",
        "poiCategories": [
          "Nightclub"
        ],
        "poiSubcategories": [],
        "duration": null,
        "referrer": null,
        "userLocation": {
          "latitude": 1.264698,
          "longitude": 103.824835
        }
      },
      {
        "timestamp": "2013-03-08T15:55:40+00:00",
        "poiId": "4b32a70cf964a520f71025e3",
        "poiCategories": [
          "Nightclub"
        ],
        "poiSubcategories": [],
        "duration": null,
        "referrer": null,
        "userLocation": {
          "latitude": 1.290786,
          "longitude": 103.845801
        }
      },
      {
        "timestamp": "2013-03-14T15:12:35+00:00",
        "poiId": "4be2d629b02ec9b63cc94dc0",
        "poiCategories": [
          "Dim Sum Restaurant"
        ],
        "poiSubcategories": [],
        "duration": null,
        "referrer": null,
        "userLocation": {
          "latitude": 1.314423,
          "longitude": 103.878296
        }
      },
      {
        "timestamp": "2013-03-15T10:12:01+00:00",
        "poiId": "4b5da988f964a520ae6529e3",
        "poiCategories": [
          "Mall"
        ],
        "poiSubcategories": [],
        "duration": null,
        "referrer": null,
        "userLocation": {
          "latitude": 1.350678,
          "longitude": 103.87275
        }
      },
      {
        "timestamp": "2013-03-17T16:41:14+00:00",
        "poiId": "4b51980df964a5204d5027e3",
        "poiCategories": [
          "Seafood Restaurant"
        ],
        "poiSubcategories": [],
        "duration": null,
        "referrer": null,
        "userLocation": {
          "latitude": 1.311446,
          "longitude": 103.874497
        }
      },
      {
        "timestamp": "2013-03-20T16:04:35+00:00",
        "poiId": "4b762527f964a520d93f2ee3",
        "poiCategories": [
          "Nightclub"
        ],
        "poiSubcategories": [],
        "duration": null,
        "referrer": null,
        "userLocation": {
          "latitude": 1.264698,
          "longitude": 103.824835
        }
      },
      {
        "timestamp": "2013-03-20T20:01:12+00:00",
        "poiId": "4d83c672f9f3a1cdb6e3a764",
        "poiCategories": [
          "Beer Garden"
        ],
        "poiSubcategories": [],
        "duration": null,
        "referrer": null,
        "userLocation": {
          "latitude": 1.264527,
          "longitude": 103.824255
        }
      },
      {
        "timestamp": "2013-03-22T08:12:00+00:00",
        "poiId": "4e6ac2fcd164c37bf4bc1538",
        "poiCategories": [
          "Clothing Store"
        ],
        "poiSubcategories": [],
        "duration": null,
        "referrer": null,
        "userLocation": {
          "latitude": 1.302752,
          "longitude": 103.836154
        }
      },
      {
        "timestamp": "2013-03-22T08:44:27+00:00",
        "poiId": "50697249e4b0cdb23126577a",
        "poiCategories": [
          "Mall"
        ],
        "poiSubcategories": [],
        "duration": null,
        "referrer": null,
        "userLocation": {
          "latitude": 1.301137,
          "longitude": 103.836387
        }
      },
      {
        "timestamp": "2013-03-27T11:11:49+00:00",
        "poiId": "4c853176ee6fef3bd6893a5c",
        "poiCategories": [
          "Mall"
        ],
        "poiSubcategories": [],
        "duration": null,
        "referrer": null,
        "userLocation": {
          "latitude": 1.315068,
          "longitude": 103.764753
        }
      },
      {
        "timestamp": "2013-03-30T17:09:14+00:00",
        "poiId": "4b762527f964a520d93f2ee3",
        "poiCategories": [
          "Nightclub"
        ],
        "poiSubcategories": [],
        "duration": null,
        "referrer": null,
        "userLocation": {
          "latitude": 1.264698,
          "longitude": 103.824835
        }
      },
      {
        "timestamp": "2013-04-03T15:11:20+00:00",
        "poiId": "4d83c672f9f3a1cdb6e3a764",
        "poiCategories": [
          "Beer Garden"
        ],
        "poiSubcategories": [],
        "duration": null,
        "referrer": null,
        "userLocation": {
          "latitude": 1.264527,
          "longitude": 103.824255
        }
      },
      {
        "timestamp": "2013-04-05T14:20:28+00:00",
        "poiId": "4c775cda93faa093a2c5f0fb",
        "poiCategories": [
          "Mall"
        ],
        "poiSubcategories": [],
        "duration": null,
        "referrer": null,
        "userLocation": {
          "latitude": 1.301253,
          "longitude": 103.837023
        }
      },
      {
        "timestamp": "2013-04-05T15:53:42+00:00",
        "poiId": "514341cbe4b0abca5d7d2250",
        "poiCategories": [
          "Nightclub"
        ],
        "poiSubcategories": [],
        "duration": null,
        "referrer": null,
        "userLocation": {
          "latitude": 1.290928,
          "longitude": 103.845716
        }
      },
      {
        "timestamp": "2013-04-06T13:43:42+00:00",
        "poiId": "4f6bf0dfe4b0541c6001a1b5",
        "poiCategories": [
          "Pool Hall"
        ],
        "poiSubcategories": [],
        "duration": null,
        "referrer": null,
        "userLocation": {
          "latitude": 1.300909,
          "longitude": 103.836041
        }
      },
      {
        "timestamp": "2013-04-06T16:04:34+00:00",
        "poiId": "4b762527f964a520d93f2ee3",
        "poiCategories": [
          "Nightclub"
        ],
        "poiSubcategories": [],
        "duration": null,
        "referrer": null,
        "userLocation": {
          "latitude": 1.264698,
          "longitude": 103.824835
        }
      },
      {
        "timestamp": "2013-04-06T20:42:03+00:00",
        "poiId": "513a060be4b03ded3956b972",
        "poiCategories": [
          "Nightclub"
        ],
        "poiSubcategories": [],
        "duration": null,
        "referrer": null,
        "userLocation": {
          "latitude": 1.264484,
          "longitude": 103.824442
        }
      },
      {
        "timestamp": "2013-04-12T11:43:19+00:00",
        "poiId": "4c384f3e93db0f474f592192",
        "poiCategories": [
          "Flea Market"
        ],
        "poiSubcategories": [],
        "duration": null,
        "referrer": null,
        "userLocation": {
          "latitude": 1.300524,
          "longitude": 103.854967
        }
      },
      {
        "timestamp": "2013-04-12T13:32:42+00:00",
        "poiId": "50312ebee4b0c51826825e73",
        "poiCategories": [
          "Bar"
        ],
        "poiSubcategories": [],
        "duration": null,
        "referrer": null,
        "userLocation": {
          "latitude": 1.299289,
          "longitude": 103.854911
        }
      },
      {
        "timestamp": "2013-04-15T12:13:18+00:00",
        "poiId": "4c775cda93faa093a2c5f0fb",
        "poiCategories": [
          "Mall"
        ],
        "poiSubcategories": [],
        "duration": null,
        "referrer": null,
        "userLocation": {
          "latitude": 1.301253,
          "longitude": 103.837023
        }
      },
      {
        "timestamp": "2013-04-15T14:19:16+00:00",
        "poiId": "4dde09c652b155583df8ce22",
        "poiCategories": [
          "Caf\u001a\u001a"
        ],
        "poiSubcategories": [],
        "duration": null,
        "referrer": null,
        "userLocation": {
          "latitude": 1.301232,
          "longitude": 103.836508
        }
      },
      {
        "timestamp": "2013-04-21T09:06:33+00:00",
        "poiId": "4b058818f964a520a7b122e3",
        "poiCategories": [
          "Mall"
        ],
        "poiSubcategories": [],
        "duration": null,
        "referrer": null,
        "userLocation": {
          "latitude": 1.264939,
          "longitude": 103.821668
        }
      },
      {
        "timestamp": "2013-04-21T10:17:04+00:00",
        "poiId": "4c384f3e93db0f474f592192",
        "poiCategories": [
          "Flea Market"
        ],
        "poiSubcategories": [],
        "duration": null,
        "referrer": null,
        "userLocation": {
          "latitude": 1.300524,
          "longitude": 103.854967
        }
      },
      {
        "timestamp": "2013-04-21T11:12:33+00:00",
        "poiId": "4b164600f964a520efb723e3",
        "poiCategories": [
          "Mall"
        ],
        "poiSubcategories": [],
        "duration": null,
        "referrer": null,
        "userLocation": {
          "latitude": 1.299666,
          "longitude": 103.854446
        }
      },
      {
        "timestamp": "2013-04-21T11:38:15+00:00",
        "poiId": "4b18f2e6f964a520acd623e3",
        "poiCategories": [
          "Multiplex"
        ],
        "poiSubcategories": [],
        "duration": null,
        "referrer": null,
        "userLocation": {
          "latitude": 1.299762,
          "longitude": 103.854371
        }
      },
      {
        "timestamp": "2013-04-21T14:45:58+00:00",
        "poiId": "4f2b7e70e4b05d297bd46a74",
        "poiCategories": [
          "Pool Hall"
        ],
        "poiSubcategories": [],
        "duration": null,
        "referrer": null,
        "userLocation": {
          "latitude": 1.298677,
          "longitude": 103.853479
        }
      },
      {
        "timestamp": "2013-04-28T10:39:06+00:00",
        "poiId": "4c775cda93faa093a2c5f0fb",
        "poiCategories": [
          "Mall"
        ],
        "poiSubcategories": [],
        "duration": null,
        "referrer": null,
        "userLocation": {
          "latitude": 1.301253,
          "longitude": 103.837023
        }
      },
      {
        "timestamp": "2013-04-28T11:07:20+00:00",
        "poiId": "516693d1e4b00896975707b3",
        "poiCategories": [
          "Restaurant"
        ],
        "poiSubcategories": [],
        "duration": null,
        "referrer": null,
        "userLocation": {
          "latitude": 1.301246,
          "longitude": 103.836873
        }
      },
      {
        "timestamp": "2013-04-30T14:44:26+00:00",
        "poiId": "514341cbe4b0abca5d7d2250",
        "poiCategories": [
          "Nightclub"
        ],
        "poiSubcategories": [],
        "duration": null,
        "referrer": null,
        "userLocation": {
          "latitude": 1.290928,
          "longitude": 103.845716
        }
      },
      {
        "timestamp": "2013-05-03T20:53:21+00:00",
        "poiId": "4effc3df6d8642ac2d377904",
        "poiCategories": [
          "Nightclub"
        ],
        "poiSubcategories": [],
        "duration": null,
        "referrer": null,
        "userLocation": {
          "latitude": 1.29117,
          "longitude": 103.844125
        }
      },
      {
        "timestamp": "2013-05-10T13:57:47+00:00",
        "poiId": "4b336d63f964a5205b1925e3",
        "poiCategories": [
          "Chinese Restaurant"
        ],
        "poiSubcategories": [],
        "duration": null,
        "referrer": null,
        "userLocation": {
          "latitude": 1.28902,
          "longitude": 103.84769
        }
      },
      {
        "timestamp": "2013-05-10T15:16:00+00:00",
        "poiId": "514341cbe4b0abca5d7d2250",
        "poiCategories": [
          "Nightclub"
        ],
        "poiSubcategories": [],
        "duration": null,
        "referrer": null,
        "userLocation": {
          "latitude": 1.290928,
          "longitude": 103.845716
        }
      },
      {
        "timestamp": "2013-05-11T18:36:30+00:00",
        "poiId": "4eca6e83be7ba4fc71d9c8a6",
        "poiCategories": [
          "Nightclub"
        ],
        "poiSubcategories": [],
        "duration": null,
        "referrer": null,
        "userLocation": {
          "latitude": 1.306302,
          "longitude": 103.828054
        }
      },
      {
        "timestamp": "2013-05-15T15:11:46+00:00",
        "poiId": "514341cbe4b0abca5d7d2250",
        "poiCategories": [
          "Nightclub"
        ],
        "poiSubcategories": [],
        "duration": null,
        "referrer": null,
        "userLocation": {
          "latitude": 1.290928,
          "longitude": 103.845716
        }
      },
      {
        "timestamp": "2013-05-15T20:02:32+00:00",
        "poiId": "4d83c672f9f3a1cdb6e3a764",
        "poiCategories": [
          "Beer Garden"
        ],
        "poiSubcategories": [],
        "duration": null,
        "referrer": null,
        "userLocation": {
          "latitude": 1.264527,
          "longitude": 103.824255
        }
      },
      {
        "timestamp": "2013-05-15T20:23:59+00:00",
        "poiId": "513a060be4b03ded3956b972",
        "poiCategories": [
          "Nightclub"
        ],
        "poiSubcategories": [],
        "duration": null,
        "referrer": null,
        "userLocation": {
          "latitude": 1.264484,
          "longitude": 103.824442
        }
      },
      {
        "timestamp": "2013-05-17T13:08:36+00:00",
        "poiId": "4c775cda93faa093a2c5f0fb",
        "poiCategories": [
          "Mall"
        ],
        "poiSubcategories": [],
        "duration": null,
        "referrer": null,
        "userLocation": {
          "latitude": 1.301253,
          "longitude": 103.837023
        }
      },
      {
        "timestamp": "2013-05-17T14:27:37+00:00",
        "poiId": "4effc3df6d8642ac2d377904",
        "poiCategories": [
          "Nightclub"
        ],
        "poiSubcategories": [],
        "duration": null,
        "referrer": null,
        "userLocation": {
          "latitude": 1.29117,
          "longitude": 103.844125
        }
      },
      {
        "timestamp": "2013-05-17T20:26:48+00:00",
        "poiId": "4e8f1329dab454671ef8d0a6",
        "poiCategories": [
          "Nightclub"
        ],
        "poiSubcategories": [],
        "duration": null,
        "referrer": null,
        "userLocation": {
          "latitude": 1.292022,
          "longitude": 103.859208
        }
      },
      {
        "timestamp": "2013-05-18T15:22:35+00:00",
        "poiId": "514341cbe4b0abca5d7d2250",
        "poiCategories": [
          "Nightclub"
        ],
        "poiSubcategories": [],
        "duration": null,
        "referrer": null,
        "userLocation": {
          "latitude": 1.290928,
          "longitude": 103.845716
        }
      },
      {
        "timestamp": "2013-06-08T12:02:43+00:00",
        "poiId": "4c775cda93faa093a2c5f0fb",
        "poiCategories": [
          "Mall"
        ],
        "poiSubcategories": [],
        "duration": null,
        "referrer": null,
        "userLocation": {
          "latitude": 1.301253,
          "longitude": 103.837023
        }
      },
      {
        "timestamp": "2013-06-11T18:45:59+00:00",
        "poiId": "4effc3df6d8642ac2d377904",
        "poiCategories": [
          "Nightclub"
        ],
        "poiSubcategories": [],
        "duration": null,
        "referrer": null,
        "userLocation": {
          "latitude": 1.29117,
          "longitude": 103.844125
        }
      },
      {
        "timestamp": "2013-06-14T15:11:17+00:00",
        "poiId": "514341cbe4b0abca5d7d2250",
        "poiCategories": [
          "Nightclub"
        ],
        "poiSubcategories": [],
        "duration": null,
        "referrer": null,
        "userLocation": {
          "latitude": 1.290928,
          "longitude": 103.845716
        }
      },
      {
        "timestamp": "2013-06-21T16:19:11+00:00",
        "poiId": "4b895722f964a520f22c32e3",
        "poiCategories": [
          "Nightclub"
        ],
        "poiSubcategories": [],
        "duration": null,
        "referrer": null,
        "userLocation": {
          "latitude": 1.291157,
          "longitude": 103.83496
        }
      },
      {
        "timestamp": "2013-07-04T15:44:58+00:00",
        "poiId": "50815727e4b0073ffa3dc5aa",
        "poiCategories": [
          "Nightclub"
        ],
        "poiSubcategories": [],
        "duration": null,
        "referrer": null,
        "userLocation": {
          "latitude": 1.290587,
          "longitude": 103.84545
        }
      },
      {
        "timestamp": "2013-07-05T15:16:51+00:00",
        "poiId": "514341cbe4b0abca5d7d2250",
        "poiCategories": [
          "Nightclub"
        ],
        "poiSubcategories": [],
        "duration": null,
        "referrer": null,
        "userLocation": {
          "latitude": 1.290928,
          "longitude": 103.845716
        }
      },
      {
        "timestamp": "2013-07-10T15:56:32+00:00",
        "poiId": "50f1ad7be4b0403bd4282e45",
        "poiCategories": [
          "Chinese Restaurant"
        ],
        "poiSubcategories": [],
        "duration": null,
        "referrer": null,
        "userLocation": {
          "latitude": 1.291053,
          "longitude": 103.846418
        }
      },
      {
        "timestamp": "2013-07-12T19:33:41+00:00",
        "poiId": "514341cbe4b0abca5d7d2250",
        "poiCategories": [
          "Nightclub"
        ],
        "poiSubcategories": [],
        "duration": null,
        "referrer": null,
        "userLocation": {
          "latitude": 1.290928,
          "longitude": 103.845716
        }
      },
      {
        "timestamp": "2013-07-19T14:40:14+00:00",
        "poiId": "514341cbe4b0abca5d7d2250",
        "poiCategories": [
          "Nightclub"
        ],
        "poiSubcategories": [],
        "duration": null,
        "referrer": null,
        "userLocation": {
          "latitude": 1.290928,
          "longitude": 103.845716
        }
      },
      {
        "timestamp": "2013-07-19T18:37:01+00:00",
        "poiId": "50815727e4b0073ffa3dc5aa",
        "poiCategories": [
          "Nightclub"
        ],
        "poiSubcategories": [],
        "duration": null,
        "referrer": null,
        "userLocation": {
          "latitude": 1.290587,
          "longitude": 103.84545
        }
      },
      {
        "timestamp": "2013-07-20T17:50:39+00:00",
        "poiId": "4b895722f964a520f22c32e3",
        "poiCategories": [
          "Nightclub"
        ],
        "poiSubcategories": [],
        "duration": null,
        "referrer": null,
        "userLocation": {
          "latitude": 1.291157,
          "longitude": 103.83496
        }
      },
      {
        "timestamp": "2013-07-20T18:04:52+00:00",
        "poiId": "4b05880cf964a5200eae22e3",
        "poiCategories": [
          "Nightclub"
        ],
        "poiSubcategories": [],
        "duration": null,
        "referrer": null,
        "userLocation": {
          "latitude": 1.291117,
          "longitude": 103.834866
        }
      },
      {
        "timestamp": "2013-07-20T18:05:24+00:00",
        "poiId": "4b895722f964a520f22c32e3",
        "poiCategories": [
          "Nightclub"
        ],
        "poiSubcategories": [],
        "duration": null,
        "referrer": null,
        "userLocation": {
          "latitude": 1.291157,
          "longitude": 103.83496
        }
      },
      {
        "timestamp": "2013-07-24T15:36:07+00:00",
        "poiId": "514341cbe4b0abca5d7d2250",
        "poiCategories": [
          "Nightclub"
        ],
        "poiSubcategories": [],
        "duration": null,
        "referrer": null,
        "userLocation": {
          "latitude": 1.290928,
          "longitude": 103.845716
        }
      },
      {
        "timestamp": "2013-08-02T14:35:45+00:00",
        "poiId": "4c0c507c009a0f474c87ecbf",
        "poiCategories": [
          "Mall"
        ],
        "poiSubcategories": [],
        "duration": null,
        "referrer": null,
        "userLocation": {
          "latitude": 1.303218,
          "longitude": 103.864633
        }
      },
      {
        "timestamp": "2013-08-08T17:16:07+00:00",
        "poiId": "4d383dfaf1b06ea8fcfa1355",
        "poiCategories": [
          "BBQ Joint"
        ],
        "poiSubcategories": [],
        "duration": null,
        "referrer": null,
        "userLocation": {
          "latitude": 1.303229,
          "longitude": 103.865063
        }
      },
      {
        "timestamp": "2013-08-14T15:11:04+00:00",
        "poiId": "514341cbe4b0abca5d7d2250",
        "poiCategories": [
          "Nightclub"
        ],
        "poiSubcategories": [],
        "duration": null,
        "referrer": null,
        "userLocation": {
          "latitude": 1.290928,
          "longitude": 103.845716
        }
      },
      {
        "timestamp": "2013-08-23T16:55:50+00:00",
        "poiId": "4b05880cf964a5200eae22e3",
        "poiCategories": [
          "Nightclub"
        ],
        "poiSubcategories": [],
        "duration": null,
        "referrer": null,
        "userLocation": {
          "latitude": 1.291117,
          "longitude": 103.834866
        }
      },
      {
        "timestamp": "2013-08-23T17:22:46+00:00",
        "poiId": "514341cbe4b0abca5d7d2250",
        "poiCategories": [
          "Nightclub"
        ],
        "poiSubcategories": [],
        "duration": null,
        "referrer": null,
        "userLocation": {
          "latitude": 1.290928,
          "longitude": 103.845716
        }
      },
      {
        "timestamp": "2013-08-25T05:33:52+00:00",
        "poiId": "4b058815f964a520acb022e3",
        "poiCategories": [
          "Mall"
        ],
        "poiSubcategories": [],
        "duration": null,
        "referrer": null,
        "userLocation": {
          "latitude": 1.291128,
          "longitude": 103.857708
        }
      },
      {
        "timestamp": "2013-09-07T11:32:57+00:00",
        "poiId": "4b932271f964a520073734e3",
        "poiCategories": [
          "Train Station"
        ],
        "poiSubcategories": [],
        "duration": null,
        "referrer": null,
        "userLocation": {
          "latitude": 1.372859,
          "longitude": 103.949332
        }
      },
      {
        "timestamp": "2013-09-07T12:01:35+00:00",
        "poiId": "4b05880bf964a520e6ad22e3",
        "poiCategories": [
          "Resort"
        ],
        "poiSubcategories": [],
        "duration": null,
        "referrer": null,
        "userLocation": {
          "latitude": 1.376194,
          "longitude": 103.953809
        }
      },
      {
        "timestamp": "2013-09-10T16:02:29+00:00",
        "poiId": "4b245182f964a520cf6524e3",
        "poiCategories": [
          "Mall"
        ],
        "poiSubcategories": [],
        "duration": null,
        "referrer": null,
        "userLocation": {
          "latitude": 1.300417,
          "longitude": 103.84981
        }
      },
      {
        "timestamp": "2013-09-10T20:47:06+00:00",
        "poiId": "513a060be4b03ded3956b972",
        "poiCategories": [
          "Nightclub"
        ],
        "poiSubcategories": [],
        "duration": null,
        "referrer": null,
        "userLocation": {
          "latitude": 1.264484,
          "longitude": 103.824442
        }
      },
      {
        "timestamp": "2013-09-13T17:36:26+00:00",
        "poiId": "514341cbe4b0abca5d7d2250",
        "poiCategories": [
          "Nightclub"
        ],
        "poiSubcategories": [],
        "duration": null,
        "referrer": null,
        "userLocation": {
          "latitude": 1.290928,
          "longitude": 103.845716
        }
      },
      {
        "timestamp": "2013-09-13T18:52:52+00:00",
        "poiId": "4effc3df6d8642ac2d377904",
        "poiCategories": [
          "Nightclub"
        ],
        "poiSubcategories": [],
        "duration": null,
        "referrer": null,
        "userLocation": {
          "latitude": 1.29117,
          "longitude": 103.844125
        }
      },
      {
        "timestamp": "2013-09-16T13:11:29+00:00",
        "poiId": "4bc83dadaf07a593d97d802d",
        "poiCategories": [
          "Food Court"
        ],
        "poiSubcategories": [],
        "duration": null,
        "referrer": null,
        "userLocation": {
          "latitude": 1.312659,
          "longitude": 103.765228
        }
      }
    ]
  },
  "pois": [
    {
      "poiId": "4cfdbb9834c1a093c1fe510e",
      "name": null,
      "categories": [
        "Factory"
      ],
      "subcategories": [],
      "location": {
        "latitude": 1.313943,
        "longitude": 103.753268,
        "address": null
      },
      "nearestStation": null,
      "rating": null,
      "deal": null
    },
    {
      "poiId": "4c5ff63d13791b8d8e5f4eaf",
      "name": null,
      "categories": [
        "Food Court"
      ],
      "subcategories": [],
      "location": {
        "latitude": 1.311866,
        "longitude": 103.759748,
        "address": null
      },
      "nearestStation": null,
      "rating": null,
      "deal": null
    },
    {
      "poiId": "4c384f3e93db0f474f592192",
      "name": null,
      "categories": [
        "Flea Market"
      ],
      "subcategories": [],
      "location": {
        "latitude": 1.300524,
        "longitude": 103.854967,
        "address": null
      },
      "nearestStation": null,
      "rating": null,
      "deal": null
    },
    {
      "poiId": "4bb9c1a6935e9521d3512790",
      "name": null,
      "categories": [
        "Mall"
      ],
      "subcategories": [],
      "location": {
        "latitude": 1.299129,
        "longitude": 103.855391,
        "address": null
      },
      "nearestStation": null,
      "rating": null,
      "deal": null
    },
    {
      "poiId": "4b645cdbf964a5205dad2ae3",
      "name": null,
      "categories": [
        "Farm"
      ],
      "subcategories": [],
      "location": {
        "latitude": 1.320581,
        "longitude": 103.708727,
        "address": null
      },
      "nearestStation": null,
      "rating": null,
      "deal": null
    },
    {
      "poiId": "4da84e4793a021ab13c61abf",
      "name": null,
      "categories": [
        "Pool Hall"
      ],
      "subcategories": [],
      "location": {
        "latitude": 1.329802,
        "longitude": 103.681328,
        "address": null
      },
      "nearestStation": null,
      "rating": null,
      "deal": null
    },
    {
      "poiId": "4e6ac2fcd164c37bf4bc1538",
      "name": null,
      "categories": [
        "Clothing Store"
      ],
      "subcategories": [],
      "location": {
        "latitude": 1.302752,
        "longitude": 103.836154,
        "address": null
      },
      "nearestStation": null,
      "rating": null,
      "deal": null
    },
    {
      "poiId": "4b1537bbf964a5206ea923e3",
      "name": null,
      "categories": [
        "Train Station"
      ],
      "subcategories": [],
      "location": {
        "latitude": 1.294471,
        "longitude": 103.805967,
        "address": null
      },
      "nearestStation": null,
      "rating": null,
      "deal": null
    },
    {
      "poiId": "4ca945d544a8224bd5462040",
      "name": null,
      "categories": [
        "Park"
      ],
      "subcategories": [],
      "location": {
        "latitude": 1.292828,
        "longitude": 103.765426,
        "address": null
      },
      "nearestStation": null,
      "rating": null,
      "deal": null
    },
    {
      "poiId": "4ec4a1b1e5fa74ea530619fc",
      "name": null,
      "categories": [
        "Mall"
      ],
      "subcategories": [],
      "location": {
        "latitude": 1.30638,
        "longitude": 103.789322,
        "address": null
      },
      "nearestStation": null,
      "rating": null,
      "deal": null
    },
    {
      "poiId": "5034adaae889bef87e8d8536",
      "name": null,
      "categories": [
        "Seafood Restaurant"
      ],
      "subcategories": [],
      "location": {
        "latitude": 1.306745,
        "longitude": 103.78855,
        "address": null
      },
      "nearestStation": null,
      "rating": null,
      "deal": null
    },
    {
      "poiId": "4b4e7e0ff964a520a7ef26e3",
      "name": null,
      "categories": [
        "General Entertainment"
      ],
      "subcategories": [],
      "location": {
        "latitude": 1.300942,
        "longitude": 103.835886,
        "address": null
      },
      "nearestStation": null,
      "rating": null,
      "deal": null
    },
    {
      "poiId": "4b189466f964a52049d423e3",
      "name": null,
      "categories": [
        "Mall"
      ],
      "subcategories": [],
      "location": {
        "latitude": 1.301339,
        "longitude": 103.8386,
        "address": null
      },
      "nearestStation": null,
      "rating": null,
      "deal": null
    },
    {
      "poiId": "4c775cda93faa093a2c5f0fb",
      "name": null,
      "categories": [
        "Mall"
      ],
      "subcategories": [],
      "location": {
        "latitude": 1.301253,
        "longitude": 103.837023,
        "address": null
      },
      "nearestStation": null,
      "rating": null,
      "deal": null
    },
    {
      "poiId": "50697249e4b0cdb23126577a",
      "name": null,
      "categories": [
        "Mall"
      ],
      "subcategories": [],
      "location": {
        "latitude": 1.301137,
        "longitude": 103.836387,
        "address": null
      },
      "nearestStation": null,
      "rating": null,
      "deal": null
    },
    {
      "poiId": "4b0d0c41f964a5206f4323e3",
      "name": null,
      "categories": [
        "Subway"
      ],
      "subcategories": [],
      "location": {
        "latitude": 1.28452,
        "longitude": 103.851335,
        "address": null
      },
      "nearestStation": null,
      "rating": null,
      "deal": null
    },
    {
      "poiId": "4ea0ec822c5b5cb4f35c7acb",
      "name": null,
      "categories": [
        "Ramen /  Noodle House"
      ],
      "subcategories": [],
      "location": {
        "latitude": 1.307541,
        "longitude": 103.833216,
        "address": null
      },
      "nearestStation": null,
      "rating": null,
      "deal": null
    },
    {
      "poiId": "4b11fc01f964a520d68723e3",
      "name": null,
      "categories": [
        "Subway"
      ],
      "subcategories": [],
      "location": {
        "latitude": 1.300609,
        "longitude": 103.838568,
        "address": null
      },
      "nearestStation": null,
      "rating": null,
      "deal": null
    },
    {
      "poiId": "4bcf09e8ef10952119f98486",
      "name": null,
      "categories": [
        "Pool Hall"
      ],
      "subcategories": [],
      "location": {
        "latitude": 1.301202,
        "longitude": 103.836856,
        "address": null
      },
      "nearestStation": null,
      "rating": null,
      "deal": null
    },
    {
      "poiId": "4bcc85e6937ca5932f3aab92",
      "name": null,
      "categories": [
        "Food Court"
      ],
      "subcategories": [],
      "location": {
        "latitude": 1.314076,
        "longitude": 103.765472,
        "address": null
      },
      "nearestStation": null,
      "rating": null,
      "deal": null
    },
    {
      "poiId": "4b0ea1f9f964a520205923e3",
      "name": null,
      "categories": [
        "Train Station"
      ],
      "subcategories": [],
      "location": {
        "latitude": 1.315291,
        "longitude": 103.765206,
        "address": null
      },
      "nearestStation": null,
      "rating": null,
      "deal": null
    },
    {
      "poiId": "4b6e30a8f964a520a1b02ce3",
      "name": null,
      "categories": [
        "Fast Food Restaurant"
      ],
      "subcategories": [],
      "location": {
        "latitude": 1.306607,
        "longitude": 103.82875,
        "address": null
      },
      "nearestStation": null,
      "rating": null,
      "deal": null
    },
    {
      "poiId": "4f5c9b0be4b06784f8a19444",
      "name": null,
      "categories": [
        "Arcade"
      ],
      "subcategories": [],
      "location": {
        "latitude": 1.301128,
        "longitude": 103.836364,
        "address": null
      },
      "nearestStation": null,
      "rating": null,
      "deal": null
    },
    {
      "poiId": "4c02034cf815a593103c0a96",
      "name": null,
      "categories": [
        "Fast Food Restaurant"
      ],
      "subcategories": [],
      "location": {
        "latitude": 1.300867,
        "longitude": 103.836282,
        "address": null
      },
      "nearestStation": null,
      "rating": null,
      "deal": null
    },
    {
      "poiId": "4b7553ecf964a52088062ee3",
      "name": null,
      "categories": [
        "Fried Chicken Joint"
      ],
      "subcategories": [],
      "location": {
        "latitude": 1.30107,
        "longitude": 103.83667,
        "address": null
      },
      "nearestStation": null,
      "rating": null,
      "deal": null
    },
    {
      "poiId": "4d4d116cf8292d43506969d6",
      "name": null,
      "categories": [
        "Tea Room"
      ],
      "subcategories": [],
      "location": {
        "latitude": 1.301124,
        "longitude": 103.836164,
        "address": null
      },
      "nearestStation": null,
      "rating": null,
      "deal": null
    },
    {
      "poiId": "4b8f5fe0f964a520c65233e3",
      "name": null,
      "categories": [
        "Food Court"
      ],
      "subcategories": [],
      "location": {
        "latitude": 1.264741,
        "longitude": 103.821788,
        "address": null
      },
      "nearestStation": null,
      "rating": null,
      "deal": null
    },
    {
      "poiId": "4c0b19d7340720a1fab68793",
      "name": null,
      "categories": [
        "Coffee Shop"
      ],
      "subcategories": [],
      "location": {
        "latitude": 1.300953,
        "longitude": 103.836422,
        "address": null
      },
      "nearestStation": null,
      "rating": null,
      "deal": null
    },
    {
      "poiId": "4b058815f964a520aeb022e3",
      "name": null,
      "categories": [
        "Mall"
      ],
      "subcategories": [],
      "location": {
        "latitude": 1.303447,
        "longitude": 103.835668,
        "address": null
      },
      "nearestStation": null,
      "rating": null,
      "deal": null
    },
    {
      "poiId": "4b66ca35f964a520f52a2be3",
      "name": null,
      "categories": [
        "Boutique"
      ],
      "subcategories": [],
      "location": {
        "latitude": 1.303054,
        "longitude": 103.835594,
        "address": null
      },
      "nearestStation": null,
      "rating": null,
      "deal": null
    },
    {
      "poiId": "4dde09c652b155583df8ce22",
      "name": null,
      "categories": [
        "Caf\u001a\u001a"
      ],
      "subcategories": [],
      "location": {
        "latitude": 1.301232,
        "longitude": 103.836508,
        "address": null
      },
      "nearestStation": null,
      "rating": null,
      "deal": null
    },
    {
      "poiId": "4fae21d7e4b0c29a763221a6",
      "name": null,
      "categories": [
        "Other Great Outdoors"
      ],
      "subcategories": [],
      "location": {
        "latitude": 1.320485,
        "longitude": 103.708734,
        "address": null
      },
      "nearestStation": null,
      "rating": null,
      "deal": null
    },
    {
      "poiId": "4fcefbabe4b074e7071afc56",
      "name": null,
      "categories": [
        "Church"
      ],
      "subcategories": [],
      "location": {
        "latitude": 1.333295,
        "longitude": 103.957293,
        "address": null
      },
      "nearestStation": null,
      "rating": null,
      "deal": null
    },
    {
      "poiId": "4c00c741360a9c740808d9a0",
      "name": null,
      "categories": [
        "Event Space"
      ],
      "subcategories": [],
      "location": {
        "latitude": 1.334993,
        "longitude": 103.959911,
        "address": null
      },
      "nearestStation": null,
      "rating": null,
      "deal": null
    },
    {
      "poiId": "4b18e995f964a52079d623e3",
      "name": null,
      "categories": [
        "Train Station"
      ],
      "subcategories": [],
      "location": {
        "latitude": 1.334504,
        "longitude": 103.961542,
        "address": null
      },
      "nearestStation": null,
      "rating": null,
      "deal": null
    },
    {
      "poiId": "4bb71a2c941ad13a084a20e3",
      "name": null,
      "categories": [
        "Food Court"
      ],
      "subcategories": [],
      "location": {
        "latitude": 1.301071,
        "longitude": 103.836905,
        "address": null
      },
      "nearestStation": null,
      "rating": null,
      "deal": null
    },
    {
      "poiId": "4b762527f964a520d93f2ee3",
      "name": null,
      "categories": [
        "Nightclub"
      ],
      "subcategories": [],
      "location": {
        "latitude": 1.264698,
        "longitude": 103.824835,
        "address": null
      },
      "nearestStation": null,
      "rating": null,
      "deal": null
    },
    {
      "poiId": "4b32a70cf964a520f71025e3",
      "name": null,
      "categories": [
        "Nightclub"
      ],
      "subcategories": [],
      "location": {
        "latitude": 1.290786,
        "longitude": 103.845801,
        "address": null
      },
      "nearestStation": null,
      "rating": null,
      "deal": null
    },
    {
      "poiId": "4be2d629b02ec9b63cc94dc0",
      "name": null,
      "categories": [
        "Dim Sum Restaurant"
      ],
      "subcategories": [],
      "location": {
        "latitude": 1.314423,
        "longitude": 103.878296,
        "address": null
      },
      "nearestStation": null,
      "rating": null,
      "deal": null
    },
    {
      "poiId": "4b5da988f964a520ae6529e3",
      "name": null,
      "categories": [
        "Mall"
      ],
      "subcategories": [],
      "location": {
        "latitude": 1.350678,
        "longitude": 103.87275,
        "address": null
      },
      "nearestStation": null,
      "rating": null,
      "deal": null
    },
    {
      "poiId": "4b51980df964a5204d5027e3",
      "name": null,
      "categories": [
        "Seafood Restaurant"
      ],
      "subcategories": [],
      "location": {
        "latitude": 1.311446,
        "longitude": 103.874497,
        "address": null
      },
      "nearestStation": null,
      "rating": null,
      "deal": null
    },
    {
      "poiId": "4d83c672f9f3a1cdb6e3a764",
      "name": null,
      "categories": [
        "Beer Garden"
      ],
      "subcategories": [],
      "location": {
        "latitude": 1.264527,
        "longitude": 103.824255,
        "address": null
      },
      "nearestStation": null,
      "rating": null,
      "deal": null
    },
    {
      "poiId": "4c853176ee6fef3bd6893a5c",
      "name": null,
      "categories": [
        "Mall"
      ],
      "subcategories": [],
      "location": {
        "latitude": 1.315068,
        "longitude": 103.764753,
        "address": null
      },
      "nearestStation": null,
      "rating": null,
      "deal": null
    },
    {
      "poiId": "514341cbe4b0abca5d7d2250",
      "name": null,
      "categories": [
        "Nightclub"
      ],
      "subcategories": [],
      "location": {
        "latitude": 1.290928,
        "longitude": 103.845716,
        "address": null
      },
      "nearestStation": null,
      "rating": null,
      "deal": null
    },
    {
      "poiId": "4f6bf0dfe4b0541c6001a1b5",
      "name": null,
      "categories": [
        "Pool Hall"
      ],
      "subcategories": [],
      "location": {
        "latitude": 1.300909,
        "longitude": 103.836041,
        "address": null
      },
      "nearestStation": null,
      "rating": null,
      "deal": null
    },
    {
      "poiId": "513a060be4b03ded3956b972",
      "name": null,
      "categories": [
        "Nightclub"
      ],
      "subcategories": [],
      "location": {
        "latitude": 1.264484,
        "longitude": 103.824442,
        "address": null
      },
      "nearestStation": null,
      "rating": null,
      "deal": null
    },
    {
      "poiId": "50312ebee4b0c51826825e73",
      "name": null,
      "categories": [
        "Bar"
      ],
      "subcategories": [],
      "location": {
        "latitude": 1.299289,
        "longitude": 103.854911,
        "address": null
      },
      "nearestStation": null,
      "rating": null,
      "deal": null
    },
    {
      "poiId": "4b058818f964a520a7b122e3",
      "name": null,
      "categories": [
        "Mall"
      ],
      "subcategories": [],
      "location": {
        "latitude": 1.264939,
        "longitude": 103.821668,
        "address": null
      },
      "nearestStation": null,
      "rating": null,
      "deal": null
    },
    {
      "poiId": "4b164600f964a520efb723e3",
      "name": null,
      "categories": [
        "Mall"
      ],
      "subcategories": [],
      "location": {
        "latitude": 1.299666,
        "longitude": 103.854446,
        "address": null
      },
      "nearestStation": null,
      "rating": null,
      "deal": null
    },
    {
      "poiId": "4b18f2e6f964a520acd623e3",
      "name": null,
      "categories": [
        "Multiplex"
      ],
      "subcategories": [],
      "location": {
        "latitude": 1.299762,
        "longitude": 103.854371,
        "address": null
      },
      "nearestStation": null,
      "rating": null,
      "deal": null
    },
    {
      "poiId": "4f2b7e70e4b05d297bd46a74",
      "name": null,
      "categories": [
        "Pool Hall"
      ],
      "subcategories": [],
      "location": {
        "latitude": 1.298677,
        "longitude": 103.853479,
        "address": null
      },
      "nearestStation": null,
      "rating": null,
      "deal": null
    },
    {
      "poiId": "516693d1e4b00896975707b3",
      "name": null,
      "categories": [
        "Restaurant"
      ],
      "subcategories": [],
      "location": {
        "latitude": 1.301246,
        "longitude": 103.836873,
        "address": null
      },
      "nearestStation": null,
      "rating": null,
      "deal": null
    },
    {
      "poiId": "4effc3df6d8642ac2d377904",
      "name": null,
      "categories": [
        "Nightclub"
      ],
      "subcategories": [],
      "location": {
        "latitude": 1.29117,
        "longitude": 103.844125,
        "address": null
      },
      "nearestStation": null,
      "rating": null,
      "deal": null
    },
    {
      "poiId": "4b336d63f964a5205b1925e3",
      "name": null,
      "categories": [
        "Chinese Restaurant"
      ],
      "subcategories": [],
      "location": {
        "latitude": 1.28902,
        "longitude": 103.84769,
        "address": null
      },
      "nearestStation": null,
      "rating": null,
      "deal": null
    },
    {
      "poiId": "4eca6e83be7ba4fc71d9c8a6",
      "name": null,
      "categories": [
        "Nightclub"
      ],
      "subcategories": [],
      "location": {
        "latitude": 1.306302,
        "longitude": 103.828054,
        "address": null
      },
      "nearestStation": null,
      "rating": null,
      "deal": null
    },
    {
      "poiId": "4e8f1329dab454671ef8d0a6",
      "name": null,
      "categories": [
        "Nightclub"
      ],
      "subcategories": [],
      "location": {
        "latitude": 1.292022,
        "longitude": 103.859208,
        "address": null
      },
      "nearestStation": null,
      "rating": null,
      "deal": null
    },
    {
      "poiId": "4b895722f964a520f22c32e3",
      "name": null,
      "categories": [
        "Nightclub"
      ],
      "subcategories": [],
      "location": {
        "latitude": 1.291157,
        "longitude": 103.83496,
        "address": null
      },
      "nearestStation": null,
      "rating": null,
      "deal": null
    },
    {
      "poiId": "50815727e4b0073ffa3dc5aa",
      "name": null,
      "categories": [
        "Nightclub"
      ],
      "subcategories": [],
      "location": {
        "latitude": 1.290587,
        "longitude": 103.84545,
        "address": null
      },
      "nearestStation": null,
      "rating": null,
      "deal": null
    },
    {
      "poiId": "50f1ad7be4b0403bd4282e45",
      "name": null,
      "categories": [
        "Chinese Restaurant"
      ],
      "subcategories": [],
      "location": {
        "latitude": 1.291053,
        "longitude": 103.846418,
        "address": null
      },
      "nearestStation": null,
      "rating": null,
      "deal": null
    },
    {
      "poiId": "4b05880cf964a5200eae22e3",
      "name": null,
      "categories": [
        "Nightclub"
      ],
      "subcategories": [],
      "location": {
        "latitude": 1.291117,
        "longitude": 103.834866,
        "address": null
      },
      "nearestStation": null,
      "rating": null,
      "deal": null
    },
    {
      "poiId": "4c0c507c009a0f474c87ecbf",
      "name": null,
      "categories": [
        "Mall"
      ],
      "subcategories": [],
      "location": {
        "latitude": 1.303218,
        "longitude": 103.864633,
        "address": null
      },
      "nearestStation": null,
      "rating": null,
      "deal": null
    },
    {
      "poiId": "4d383dfaf1b06ea8fcfa1355",
      "name": null,
      "categories": [
        "BBQ Joint"
      ],
      "subcategories": [],
      "location": {
        "latitude": 1.303229,
        "longitude": 103.865063,
        "address": null
      },
      "nearestStation": null,
      "rating": null,
      "deal": null
    },
    {
      "poiId": "4b058815f964a520acb022e3",
      "name": null,
      "categories": [
        "Mall"
      ],
      "subcategories": [],
      "location": {
        "latitude": 1.291128,
        "longitude": 103.857708,
        "address": null
      },
      "nearestStation": null,
      "rating": null,
      "deal": null
    },
    {
      "poiId": "4b932271f964a520073734e3",
      "name": null,
      "categories": [
        "Train Station"
      ],
      "subcategories": [],
      "location": {
        "latitude": 1.372859,
        "longitude": 103.949332,
        "address": null
      },
      "nearestStation": null,
      "rating": null,
      "deal": null
    },
    {
      "poiId": "4b05880bf964a520e6ad22e3",
      "name": null,
      "categories": [
        "Resort"
      ],
      "subcategories": [],
      "location": {
        "latitude": 1.376194,
        "longitude": 103.953809,
        "address": null
      },
      "nearestStation": null,
      "rating": null,
      "deal": null
    },
    {
      "poiId": "4b245182f964a520cf6524e3",
      "name": null,
      "categories": [
        "Mall"
      ],
      "subcategories": [],
      "location": {
        "latitude": 1.300417,
        "longitude": 103.84981,
        "address": null
      },
      "nearestStation": null,
      "rating": null,
      "deal": null
    },
    {
      "poiId": "4bc83dadaf07a593d97d802d",
      "name": null,
      "categories": [
        "Food Court"
      ],
      "subcategories": [],
      "location": {
        "latitude": 1.312659,
        "longitude": 103.765228,
        "address": null
      },
      "nearestStation": null,
      "rating": null,
      "deal": null
    }
  ]
}